tidymut/__init__.py
tidymut/cleaners/__init__.py
tidymut/cleaners/base_config.py
tidymut/cleaners/basic_cleaners.py
tidymut/cleaners/cdna_proteolysis_cleaner.py
tidymut/cleaners/cdna_proteolysis_custom_cleaners.py
tidymut/cleaners/ddg_dtm_cleaners.py
tidymut/cleaners/human_domainome_custom_cleaners.py
tidymut/cleaners/human_domainome_sup2_cleaner.py
tidymut/cleaners/human_domainome_sup4_cleaner.py
tidymut/cleaners/protein_gym_cleaner.py
tidymut/cleaners/protein_gym_custom_cleaners.py
tidymut/core/__init__.py
tidymut/core/alphabet.py
tidymut/core/codon.py
tidymut/core/constants.py
tidymut/core/dataset.py
tidymut/core/mutation.py
tidymut/core/pipeline.py
tidymut/core/sequence.py
tidymut/core/types.py
tidymut/utils/__init__.py
tidymut/utils/cleaner_workers.py
tidymut/utils/data_source.py
tidymut/utils/dataset_builders.py
tidymut/utils/label_resolvers.py
tidymut/utils/mutation_converter.py
tidymut/utils/raw_data_downloader.py
tidymut/utils/sequence_io.py
tidymut/utils/type_converter.py
tidymut-0.4.0.dist-info/licenses/LICENSE
tidymut-0.4.0.dist-info/METADATA
tidymut-0.4.0.dist-info/WHEEL
tidymut-0.4.0.dist-info/top_level.txt
tidymut-0.4.0.dist-info/RECORD
