Metadata-Version: 2.4
Name: tidymut
Version: 0.4.0
Summary: An efficient framework for tidying and standardizing protein mutation data.
Author-email: Yuxiang Tang <845351766@qq.com>
License: BSD 3-Clause License
Project-URL: Repository, https://github.com/xulab-research/TidyMut
Keywords: protein,mutation,tidy,framework,pipeline
Classifier: Development Status :: 3 - Alpha
Classifier: Intended Audience :: Science/Research
Classifier: Programming Language :: Python :: 3 :: Only
Classifier: Programming Language :: Python :: 3.13
Classifier: Operating System :: OS Independent
Classifier: Topic :: Scientific/Engineering :: Bio-Informatics
Classifier: Topic :: Software Development :: Libraries :: Python Modules
Classifier: Typing :: Typed
Requires-Python: >=3.13
License-File: LICENSE
Requires-Dist: joblib>=1.5.0
Requires-Dist: numpy>=2.1.0
Requires-Dist: pandas>=2.2.0
Requires-Dist: tqdm>=4.60.0
Requires-Dist: python-dateutil>=2.8.2
Requires-Dist: tzdata>=2022.7
Requires-Dist: requests>=2.30
Provides-Extra: test
Requires-Dist: pytest>=8.0.0; extra == "test"
Requires-Dist: pytest-cov>=6.0.0; extra == "test"
Provides-Extra: dev
Requires-Dist: pytest>=8.0.0; extra == "dev"
Requires-Dist: pytest-cov>=6.0.0; extra == "dev"
Requires-Dist: sphinx>=8.0.0; extra == "dev"
Requires-Dist: sphinx-autobuild>=2024.10.0; extra == "dev"
Requires-Dist: sphinx_rtd_theme>=3.0.0; extra == "dev"
Requires-Dist: twine>=6.0.0; extra == "dev"
Requires-Dist: gitpython; extra == "dev"
Requires-Dist: pygithub; extra == "dev"
Requires-Dist: jinja2; extra == "dev"
Dynamic: license-file
